dj_redis_panel/__init__.py
dj_redis_panel/admin.py
dj_redis_panel/apps.py
dj_redis_panel/encoding_utils.py
dj_redis_panel/models.py
dj_redis_panel/redis_utils.py
dj_redis_panel/urls.py
dj_redis_panel/views.py
dj_redis_panel/templates/admin/dj_redis_panel/base.html
dj_redis_panel/templates/admin/dj_redis_panel/index.html
dj_redis_panel/templates/admin/dj_redis_panel/instance_overview.html
dj_redis_panel/templates/admin/dj_redis_panel/key_add.html
dj_redis_panel/templates/admin/dj_redis_panel/key_detail.html
dj_redis_panel/templates/admin/dj_redis_panel/key_detail_add.html
dj_redis_panel/templates/admin/dj_redis_panel/key_detail_pagination.html
dj_redis_panel/templates/admin/dj_redis_panel/key_detail_pagination_info.html
dj_redis_panel/templates/admin/dj_redis_panel/key_detail_value_hash.html
dj_redis_panel/templates/admin/dj_redis_panel/key_detail_value_list.html
dj_redis_panel/templates/admin/dj_redis_panel/key_detail_value_set.html
dj_redis_panel/templates/admin/dj_redis_panel/key_detail_value_string.html
dj_redis_panel/templates/admin/dj_redis_panel/key_detail_value_zset.html
dj_redis_panel/templates/admin/dj_redis_panel/key_search.html
dj_redis_panel/templates/admin/dj_redis_panel/styles.css
dj_redis_panel-0.7.3.dist-info/licenses/LICENSE
dj_redis_panel-0.7.3.dist-info/METADATA
dj_redis_panel-0.7.3.dist-info/WHEEL
dj_redis_panel-0.7.3.dist-info/top_level.txt
dj_redis_panel-0.7.3.dist-info/RECORD
