Metadata-Version: 2.4
Name: dj-redis-panel
Version: 0.7.3
Summary: A Django Admin panel for browsing and inspecting Redis keys
Author: Yasser Toruno
Maintainer: Yasser Toruno
License: MIT
Project-URL: Homepage, https://yassi.github.io/dj-redis-panel/
Project-URL: Documentation, https://yassi.github.io/dj-redis-panel/
Project-URL: Repository, https://github.com/yassi/dj-redis-panel
Project-URL: Bug Tracker, https://github.com/yassi/dj-redis-panel/issues
Keywords: django,redis,admin,panel,database,key-value
Classifier: Framework :: Django
Classifier: Framework :: Django :: 4.2
Classifier: Framework :: Django :: 5.0
Classifier: Framework :: Django :: 5.1
Classifier: Framework :: Django :: 5.2
Classifier: Framework :: Django :: 6.0
Classifier: License :: OSI Approved :: MIT License
Classifier: Programming Language :: Python :: 3.9
Classifier: Programming Language :: Python :: 3.10
Classifier: Programming Language :: Python :: 3.11
Classifier: Programming Language :: Python :: 3.12
Classifier: Programming Language :: Python :: 3.13
Classifier: Programming Language :: Python :: 3.14
Classifier: Operating System :: OS Independent
Classifier: Intended Audience :: Developers
Classifier: Topic :: Software Development :: Libraries :: Application Frameworks
Requires-Python: >=3.9
License-File: LICENSE
Requires-Dist: Django>=4.2
Requires-Dist: redis>=4.0
Provides-Extra: dev
Requires-Dist: pytest>=7.0.0; extra == "dev"
Requires-Dist: pytest-django>=4.5.0; extra == "dev"
Requires-Dist: pytest-cov>=4.0.0; extra == "dev"
Requires-Dist: pytest-xdist>=3.2.0; extra == "dev"
Provides-Extra: build
Requires-Dist: build>=1.0.0; extra == "build"
Requires-Dist: twine>=4.0.0; extra == "build"
Dynamic: license-file
